toto_client/__init__.py
toto_client/toto_client.py
toto_client-0.1.3.dist-info/LICENSE
toto_client-0.1.3.dist-info/WHEEL
toto_client-0.1.3.dist-info/METADATA
toto_client-0.1.3.dist-info/RECORD
