Metadata-Version: 2.1
Name: toto-client
Version: 0.1.3
Summary: 
Author: R2 Factory
Author-email: contact@r2-factory.com
Requires-Python: ==3.8.13
Classifier: Programming Language :: Python :: 3
Requires-Dist: google-auth (>=2.15.0,<3.0.0)
Requires-Dist: requests (>=2.28.1,<3.0.0)
